automaps/__init__.py
automaps/app.py
automaps/automapsconf.py
automaps/confutils.py
automaps/db.py
automaps/fileserver.py
automaps/logutils.py
automaps/maptype.py
automaps/selector.py
automaps/start_frontend.py
automaps/start_qgis_worker.py
automaps/start_registry.py
automaps/_qgis/__init__.py
automaps/_qgis/export.py
automaps/_qgis/layout.py
automaps/_qgis/project.py
automaps/_qgis/start_qgis.py
automaps/data/demo/automapsconf.py
automaps/data/demo/automapsconf_poly.py
automaps/data/demo/db.py
automaps/data/demo/demo_data.gpkg
automaps/data/demo/demo_project.qgz
automaps/data/demo/generate_poly.py
automaps/data/demo/.streamlit/config.toml
automaps/generators/__init__.py
automaps/generators/base.py
automaps/messaging/__init__.py
automaps/messaging/client.py
automaps/messaging/registry.py
automaps/messaging/worker.py
automaps/scripts/__init__.py
automaps/scripts/project.py
automaps-1.0.5.dist-info/LICENSE
automaps-1.0.5.dist-info/METADATA
automaps-1.0.5.dist-info/WHEEL
automaps-1.0.5.dist-info/entry_points.txt
automaps-1.0.5.dist-info/top_level.txt
automaps-1.0.5.dist-info/RECORD
