Metadata-Version: 2.1
Name: automaps
Version: 1.0.5
Summary: Automatically generate customized and ready to print maps
Home-page: https://github.com/itsviennaregion/automaps
Author: Roland Lukesch
Author-email: roland.lukesch@its-viennaregion.at
License: MIT
Platform: UNKNOWN
Classifier: License :: OSI Approved :: MIT License
Classifier: Programming Language :: Python :: 3
Classifier: Programming Language :: Python :: 3.8
Requires-Python: >=3.8
Requires-Dist: Jinja2 (>=3.1.1)
Requires-Dist: Pillow (>=9.1.0)
Requires-Dist: SQLAlchemy (>=1.4.35)
Requires-Dist: click (<8.1,>=8.0.4)
Requires-Dist: pandas (>=1.4.2)
Requires-Dist: protobuf (<4,>=3.20)
Requires-Dist: psycopg2-binary (>=2.9.3)
Requires-Dist: pyzmq (>=22.3.0)
Requires-Dist: streamlit (>=1.8.1)
Requires-Dist: traitlets (>=5)
